dynamic_pybloom
