Metadata-Version: 1.1
Name: dynamic-pybloom
Version: 3.1.3
Summary: Dynamic Pybloom: A Suite of Probabilistic Data Structures
Home-page: http://github.com/srf5132/dynamic-pybloom/
Author: srf5132
Author-email: srf5132@gmail.com
License: MIT License
Keywords: data structures,bloom filter,bloom,filter,probabilistic,set
Platform: any
Classifier: Intended Audience :: Developers
Classifier: License :: OSI Approved :: MIT License
Classifier: Programming Language :: Python
Classifier: Programming Language :: Python :: 3
Classifier: Operating System :: OS Independent
Classifier: Topic :: Utilities
Classifier: Topic :: Database :: Database Engines/Servers
Classifier: Topic :: Software Development :: Libraries :: Python Modules
